medsegpy/__init__.py
medsegpy/config.py
medsegpy/glob_constants.py
medsegpy/losses.py
medsegpy/cross_validation/__init__.py
medsegpy/cross_validation/create_cv_bins.py
medsegpy/cross_validation/cv_util.py
medsegpy/data/__init__.py
medsegpy/data/build.py
medsegpy/data/catalog.py
medsegpy/data/data_loader.py
medsegpy/data/data_utils.py
medsegpy/data/fname_parsers.py
medsegpy/data/im_gens.py
medsegpy/data/datasets/__init__.py
medsegpy/data/datasets/abct.py
medsegpy/data/datasets/builtin.py
medsegpy/data/datasets/oai.py
medsegpy/data/datasets/qdess_mri.py
medsegpy/data/transforms/__init__.py
medsegpy/data/transforms/transform.py
medsegpy/data/transforms/transform_gen.py
medsegpy/engine/__init__.py
medsegpy/engine/callbacks.py
medsegpy/engine/defaults.py
medsegpy/engine/trainer.py
medsegpy/evaluation/__init__.py
medsegpy/evaluation/build.py
medsegpy/evaluation/ct_evaluation.py
medsegpy/evaluation/evaluator.py
medsegpy/evaluation/metrics.py
medsegpy/evaluation/qdess_evaluation.py
medsegpy/evaluation/sem_seg_evaluation.py
medsegpy/loss/__init__.py
medsegpy/loss/classification.py
medsegpy/loss/utils.py
medsegpy/modeling/__init__.py
medsegpy/modeling/build.py
medsegpy/modeling/initializer_utils.py
medsegpy/modeling/loading.py
medsegpy/modeling/model.py
medsegpy/modeling/model_utils.py
medsegpy/modeling/ssl_utils.py
medsegpy/modeling/unet_3d_model.py
medsegpy/modeling/deeplab_2d/__init__.py
medsegpy/modeling/deeplab_2d/deeplab_model.py
medsegpy/modeling/layers/__init__.py
medsegpy/modeling/layers/attention.py
medsegpy/modeling/layers/convolutional.py
medsegpy/modeling/layers/normalization.py
medsegpy/modeling/layers/pooling.py
medsegpy/modeling/layers/serialization.py
medsegpy/modeling/layers/upsampling.py
medsegpy/modeling/meta_arch/__init__.py
medsegpy/modeling/meta_arch/build.py
medsegpy/modeling/meta_arch/deeplabv3.py
medsegpy/modeling/meta_arch/fc_densenet.py
medsegpy/modeling/meta_arch/inpainting_and_seg_unet.py
medsegpy/modeling/meta_arch/unet.py
medsegpy-0.0.1.dist-info/METADATA
medsegpy-0.0.1.dist-info/WHEEL
medsegpy-0.0.1.dist-info/top_level.txt
medsegpy-0.0.1.dist-info/RECORD
